[{"class_name": "focused", "bbox": "279 405 430 568", "used": true}, {"class_name": "curious", "bbox": "56 406 171 526", "used": true}, {"class_name": "curious", "bbox": "540 431 618 510", "used": true}, {"class_name": "curious", "bbox": "636 428 712 498", "used": true}, {"class_name": "curious", "bbox": "743 444 833 538", "used": true}, {"class_name": "curious", "bbox": "807 440 864 501", "used": true}, {"class_name": "curious", "bbox": "885 429 963 513", "used": true}, {"class_name": "curious", "bbox": "1045 452 1110 520", "used": true}, {"class_name": "sad", "bbox": "1068 441 1129 503", "used": true}]